{
  "$schema": "https://json-schema.org/draft/2020-12/schema",
  "module": "provider.team",
  "description": "Explicit UI contract for the Provider portal /team route.",

  "route": {
    "portal": "provider",
    "path": "/team",
    "html_entry": "portals/provider.html"
  },

  "shell_overrides": {
    "currentTitle": "Team",
    "breadcrumb": ["Provider", "Org", "Team"],
    "active_sidebar_item": "team"
  },

  "page": {
    "header": {
      "component": "PageHeader",
      "title": "Team",
      "subtitle": "Members of your provider org.",
      "actions": [
        { "kind": "Btn", "variant": "primary", "icon": "plus", "label": "Invite", "test_id": "provider.team.action.invite" }
      ]
    },

    "data_table": {
      "component": "DataTable",
      "row_click_bound": false,
      "columns": [
        {
          "key": "name", "label": "Member",
          "cell": {
            "kind": "stack",
            "class": "p-cell-stack",
            "lines": [
              { "binding": "name",  "class": "p-cell-strong" },
              { "binding": "email", "class": "p-cell-meta" }
            ]
          }
        },
        { "key": "role", "label": "Role", "width": 130, "cell": { "kind": "tag", "class": "p-tag", "binding": "role" } }
      ]
    }
  },

  "icons_used": ["plus"],

  "interactions": [
    { "id": "invite", "trigger_test_id": "provider.team.action.invite", "effect": "open_invite_modal" }
  ],

  "empty_states": {
    "no_rows": { "body_text": "Couldn't load team." }
  },

  "non_negotiables": [
    "Header has only ONE action button (primary 'Invite').",
    "No StatCards and no FilterBar on this page in v0.4.",
    "Table has only TWO columns: Member (name + email stack) and Role (tag).",
    "Role taxonomy on this page: owner / editor / service. Production may colour-code; v0.4 uses uniform tag colour.",
    "Member name + email use the standard p-cell-stack pattern (strong over meta).",
    "DataTable rows are non-interactive in v0.4 — do NOT bind onRowClick.",
    "An org must always have at least one owner — server enforces; SPA must reflect by disabling the demote/remove buttons for the only owner."
  ]
}
